source_marketo/__init__.py
source_marketo/manifest.yaml
source_marketo/run.py
source_marketo/schemas/activity_types.json
source_marketo/schemas/campaigns.json
source_marketo/schemas/leads.json
source_marketo/schemas/lists.json
source_marketo/schemas/programs.json
source_marketo/schemas/segmentations.json
source_marketo/source.py
source_marketo/spec.json
source_marketo/utils.py
airbyte_source_marketo-1.4.39.dist-info/METADATA
airbyte_source_marketo-1.4.39.dist-info/WHEEL
airbyte_source_marketo-1.4.39.dist-info/entry_points.txt
airbyte_source_marketo-1.4.39.dist-info/RECORD
