Metadata-Version: 2.1
Name: airbyte-source-marketo
Version: 1.4.39
Summary: Source implementation for Marketo.
Home-page: https://airbyte.com
License: ELv2
Author: Airbyte
Author-email: contact@airbyte.io
Requires-Python: >=3.9,<3.12
Classifier: License :: Other/Proprietary License
Classifier: Programming Language :: Python :: 3
Classifier: Programming Language :: Python :: 3.9
Classifier: Programming Language :: Python :: 3.10
Classifier: Programming Language :: Python :: 3.11
Requires-Dist: airbyte-cdk (==2.3.0)
Project-URL: Documentation, https://docs.airbyte.com/integrations/sources/marketo
Project-URL: Repository, https://github.com/airbytehq/airbyte
